setup.py
sina/__init__.py
sina.egg-info/PKG-INFO
sina.egg-info/SOURCES.txt
sina.egg-info/dependency_links.txt
sina.egg-info/not-zip-safe
sina.egg-info/requires.txt
sina.egg-info/top_level.txt