Metadata-Version: 2.1
Name: sina
Version: 0.0.1
Summary: Search Indexed Nomenclature Associations
Home-page: https://github.com/dicaso/sina
Author: Christophe Van Neste
Author-email: christophe.vanneste@kaust.edu.sa
License: MIT
Platform: UNKNOWN
Requires-Python: >3.6
Provides-Extra: documentation
